barq/__init__.py
barq/barq_pb2.py
barq/barq_pb2_grpc.py
barq/client.py
barq/grpc_client.py
barq_sdk_python-0.1.0.dist-info/METADATA
barq_sdk_python-0.1.0.dist-info/WHEEL
barq_sdk_python-0.1.0.dist-info/RECORD
