Metadata-Version: 2.4
Name: barq-sdk-python
Version: 0.1.0
Summary: Python client for Barq DB
Project-URL: Homepage, https://github.com/YASSERRMD/barq-db
Author: Barq DB Contributors
Requires-Python: >=3.8
Requires-Dist: grpcio>=1.50.0
Requires-Dist: httpx>=0.23
Requires-Dist: protobuf>=4.21.0
